{
  "EXTENSION.JMCMODLIB.UI.MOD_SETTINGS_TAB": "모드 설정",
  "EXTENSION.JMCMODLIB.UI.MOD_SETTINGS_TITLE": "모드 설정",
  "EXTENSION.JMCMODLIB.UI.MOD_SETTINGS_DESCRIPTION": "등록된 모드 설정을 여기에서 조정합니다. 변경 사항은 즉시 저장됩니다.",
  "EXTENSION.JMCMODLIB.UI.CHANGES_SAVED_IMMEDIATELY": "변경 사항은 즉시 저장됩니다.",
  "EXTENSION.JMCMODLIB.UI.NO_CONFIG_MODS": "현재 설정 가능한 항목이 있는 등록된 모드가 없습니다.",
  "EXTENSION.JMCMODLIB.UI.NO_MANAGED_ASSEMBLY": "이 모드는 로드된 관리 어셈블리가 없어 설정을 표시할 수 없습니다.",
  "EXTENSION.JMCMODLIB.UI.NO_CONFIG_ENTRIES": "이 모드에는 현재 표시할 설정 항목이 없습니다.",
  "EXTENSION.JMCMODLIB.UI.AUTHOR_LABEL": "제작자",
  "EXTENSION.JMCMODLIB.UI.VERSION_LABEL": "버전",
  "EXTENSION.JMCMODLIB.UI.RESTART_REQUIRED": "완전히 적용하려면 게임을 다시 시작해야 합니다.",
  "EXTENSION.JMCMODLIB.UI.EXPAND": "펼치기",
  "EXTENSION.JMCMODLIB.UI.COLLAPSE": "접기",
  "EXTENSION.JMCMODLIB.UI.EXPAND_ALL": "모두 펼치기",
  "EXTENSION.JMCMODLIB.UI.COLLAPSE_ALL": "모두 접기",
  "EXTENSION.JMCMODLIB.UI.RESET_MOD": "이 모드 초기화",
  "EXTENSION.JMCMODLIB.UI.RESET": "초기화",
  "EXTENSION.JMCMODLIB.UI.CLOSE": "닫기",
  "EXTENSION.JMCMODLIB.UI.KEYBIND_LISTENING": "새 키, 키 조합 또는 버튼을 누르세요...",
  "EXTENSION.JMCMODLIB.UI.KEYBIND_UNBOUND": "할당되지 않음",
  "EXTENSION.JMCMODLIB.UI.STEAM_INPUT_MANAGED": "Steam Input에서 바인딩",
  "EXTENSION.JMCMODLIB.UI.COLOR_SELECT": "선택",
  "EXTENSION.JMCMODLIB.UI.CONFIG_TITLE": "{modName} 설정",
  "EXTENSION.JMCMODLIB.UI.UNSUPPORTED_TYPE": "지원하지 않는 타입: {type}",
  "EXTENSION.JMCMODLIB.UI.SECRET_SET_BUTTON": "Set / Update",
  "EXTENSION.JMCMODLIB.UI.SECRET_CLEAR_BUTTON": "Clear",
  "EXTENSION.JMCMODLIB.UI.SECRET_STATUS_MISSING": "Not saved",
  "EXTENSION.JMCMODLIB.UI.SECRET_STATUS_SAVED": "Saved",
  "EXTENSION.JMCMODLIB.UI.SECRET_STATUS_UNAVAILABLE": "Secure storage is not supported on this platform.",
  "EXTENSION.JMCMODLIB.UI.SECRET_STATUS_WEAK": "Only weak file protection is available.",
  "EXTENSION.JMCMODLIB.UI.SECRET_STATUS_SAVED_WEAK": "Saved with weak file protection.",
  "EXTENSION.JMCMODLIB.UI.SECRET_STATUS_ACCESS_DENIED": "Access denied.",
  "EXTENSION.JMCMODLIB.UI.SECRET_STATUS_WEAK_NOT_ALLOWED": "Weak file protection is not allowed for this Secret.",
  "EXTENSION.JMCMODLIB.UI.SECRET_STATUS_BACKEND_ERROR": "Secret backend error.",
  "EXTENSION.JMCMODLIB.UI.SECRET_INPUT_CONFIRM": "Save",
  "EXTENSION.JMCMODLIB.UI.SECRET_INPUT_CANCEL": "Cancel",
  "EXTENSION.JMCMODLIB.UI.SECRET_INPUT_PLACEHOLDER": "Enter secret value",
  "EXTENSION.JMCMODLIB.UI.SECRET_INPUT_EMPTY": "Secret value cannot be empty.",
  "EXTENSION.JMCMODLIB.UI.SECRET_INPUT_UNAVAILABLE_TITLE": "Secret storage unavailable",
  "EXTENSION.JMCMODLIB.UI.SECRET_INPUT_UNAVAILABLE_BODY": "This platform does not currently provide secure Secret storage for this entry.",
  "EXTENSION.JMCMODLIB.UI.SECRET_INPUT_WEAK_WARNING": "Current platform cannot use system secure storage. Saving will use weak file protection and is not recommended on shared devices.",
  "EXTENSION.JMCMODLIB.UI.SECRET_CLEAR_TITLE": "Clear Secret",
  "EXTENSION.JMCMODLIB.UI.SECRET_CLEAR_BODY": "Clear the saved Secret for {name}?",
  "EXTENSION.JMCMODLIB.UI.SECRET_SAVE_FAILED": "Failed to save Secret: {status}",
  "EXTENSION.JMCMODLIB.UI.SECRET_CLEAR_FAILED": "Failed to clear Secret: {status}",
  "EXTENSION.JMCMODLIB.UI.GROUP.JMCMODLIB": "JmcModLib",
  "EXTENSION.JMCMODLIB.UI.AUTO_MOD_MANAGER_RESTART_BUTTON.NAME": "모드 관리자에 다시 시작 버튼 표시",
  "EXTENSION.JMCMODLIB.UI.AUTO_MOD_MANAGER_RESTART_BUTTON.DESCRIPTION": "모드를 켜거나 끌 때 게임 다시 시작이 필요한 경우 오른쪽에 다시 시작 버튼을 자동으로 표시합니다.",
  "EXTENSION.JMCMODLIB.RESTART.CONFIRM_TITLE": "게임을 다시 시작할까요?",
  "EXTENSION.JMCMODLIB.RESTART.CONFIRM_BODY": "현재 설정을 저장한 뒤 게임을 종료하고 다시 시작합니다.",
  "EXTENSION.JMCMODLIB.RESTART.CONFIRM_BUTTON": "다시 시작",
  "EXTENSION.JMCMODLIB.RESTART.CANCEL_BUTTON": "취소",
  "EXTENSION.JMCMODLIB.RESTART.CLOSE_BUTTON": "닫기",
  "EXTENSION.JMCMODLIB.RESTART.UNSUPPORTED_TITLE": "다시 시작할 수 없음",
  "EXTENSION.JMCMODLIB.RESTART.UNSUPPORTED_BODY": "{platform}에서는 자동 다시 시작을 지원하지 않습니다. 게임을 직접 다시 시작해 주세요."
}
